{
    "Energy": {
        "next": [
            "[JumpBack]LeaveCurrentPage",
            "[JumpBack]CloseGift",
            "[JumpBack]CloseByClickBlank",
            "[JumpBack]CardPage",
            "UseEnergy"
        ]
    },
    "UseEnergy": {
        "next": [
            "[JumpBack]PigByEnergy", // 杀猪
            "[JumpBack]GoldByEnergy", // 挖金币
            "[JumpBack]IronByEnergy", // 挖铁
            "[JumpBack]GravelByEnergy", // 挖砂
            "LeaveCurrentPage"
        ]
    },
    "PigByEnergy": {
        "enabled": false,
        "next": [
            "EnterForestCountry",
            "[JumpBack]WorldPage",
            "[JumpBack]ChooseLowerFloor",
            "[JumpBack]SwipeSearchForestCountry"
        ],
        "max_hit": 1
    },
    "GoldByEnergy": {
        "enabled": false,
        "next": [
            "[JumpBack]NotePage",
            "[JumpBack]ExploreResourcePage",
            "ChooseGold"
        ],
        "max_hit": 1
    },
    "IronByEnergy": {
        "enabled": false,
        "next": [
            "[JumpBack]NotePage",
            "[JumpBack]ExploreResourcePage",
            "ChooseIron"
        ],
        "max_hit": 1
    },
    "GravelByEnergy": {
        "enabled": false,
        "next": [
            "[JumpBack]NotePage",
            "[JumpBack]ExploreResourcePage",
            "ChooseGravel"
        ],
        "max_hit": 1
    },
    "ExploreResourcePage": {
        "recognition": {
            "type": "OCR",
            "param": {
                "roi": [
                    5,
                    519,
                    413,
                    170
                ],
                "expected": [
                    "地图探索"
                ]
            }
        },
        "action": {
            "type": "Click"
        }
    },
    "ChooseLowerFloor": {
        "recognition": {
            "type": "TemplateMatch",
            "param": {
                "roi": [
                    26,
                    999,
                    43,
                    46
                ],
                "template": [
                    "button/lower_floor.png"
                ]
            }
        },
        "action": {
            "type": "Click"
        },
        "post_delay": 2000,
        "max_hit": 1
    },
    "EnterForestCountry": {
        "recognition": {
            "type": "OCR",
            "param": {
                "expected": [
                    "森之国"
                ]
            }
        },
        "action": {
            "type": "Click"
        },
        "next": [
            "[JumpBack]Loading",
            "[JumpBack]Chat",
            "OpenMap"
        ]
    },
    "SwipeSearchForestCountry": {
        "next": [
            "SwipeLeftSearchForestCountry",
            "SwipeRightSearchForestCountry",
            "SwipeUpSearchForestCountry",
            "SwipeDownSearchForestCountry",
            "End"
        ]
    },
    "SwipeLeftSearchForestCountry": {
        "next": [
            "SwipeLeft"
        ],
        "max_hit": 5
    },
    "SwipeRightSearchForestCountry": {
        "next": [
            "SwipeRight"
        ],
        "max_hit": 5
    },
    "SwipeUpSearchForestCountry": {
        "next": [
            "SwipeUp"
        ],
        "max_hit": 5
    },
    "SwipeDownSearchForestCountry": {
        "next": [
            "SwipeDown"
        ],
        "max_hit": 5
    },
    "OpenMap": {
        "recognition": {
            "type": "OCR",
            "param": {
                "roi": [
                    523,
                    244,
                    199,
                    54
                ],
                "expected": [
                    "\\(\\d+,\\d+\\)" // 匹配任意坐标
                ]
            }
        },
        "action": {
            "type": "Click",
            "param": {
                "target": [
                    562,
                    135,
                    116,
                    89
                ]
            }
        },
        "next": [
            "[JumpBack]FindInMap",
            "[JumpBack]KillPig",
            "[JumpBack]SlimeSearch",
            "End"
        ],
        "post_delay": 2000
    },
    "FindInMap": {
        "recognition": {
            "type": "OCR",
            "param": {
                "roi": [
                    560,
                    35,
                    152,
                    192
                ],
                "expected": [
                    "传送门"
                ]
            }
        },
        "next": [
            "FindPig",
            "[JumpBack]SwipeMapRight",
            "[JumpBack]SwipeMapUp",
            "[JumpBack]SwipeMapLeft"
        ]
    },
    "SwipeMapRight": {
        "next": [
            "SwipeRight"
        ],
        "max_hit": 10
    },
    "SwipeMapUp": {
        "next": [
            "SwipeUp"
        ],
        "max_hit": 5
    },
    "SwipeMapLeft": {
        "next": [
            "SwipeLeft"
        ],
        "max_hit": 10
    },
    "FindPig": {
        "recognition": {
            "type": "OCR",
            "param": {
                "expected": [
                    "雕鸮营地"
                ]
            }
        },
        "action": {
            "type": "Click"
        },
        "next": [
            "LeaveCurrentPage"
        ]
    },
    "ExhaustEnergy": {
        "recognition": {
            "type": "OCR",
            "param": {
                "expected": [
                    "体力不足"
                ]
            }
        },
        "next": [
            "End"
        ]
    },
    "KillPig": {
        "recognition": {
            "type": "TemplateMatch",
            "param": {
                "template": [
                    "materials/pig.png"
                ],
                "index": 0
            }
        },
        "action": {
            "type": "Click"
        },
        "next": [
            "ExhaustEnergy",
            "EndAutoPage",
            "[JumpBack]AutoButton",
            "[JumpBack]StartAutoPage"
        ],
        "max_hit": 1
    },
    "ChooseGold": {
        "recognition": {
            "type": "TemplateMatch",
            "param": {
                "roi": [
                    22,
                    270,
                    316,
                    68
                ],
                "template": [
                    "materials/gold_light.png",
                    "materials/gold_night.png"
                ]
            }
        },
        "action": {
            "type": "Click"
        },
        "next": [
            "DepartForResource"
        ]
    },
    "ChooseIron": {
        "recognition": {
            "type": "TemplateMatch",
            "param": {
                "roi": [
                    22,
                    270,
                    316,
                    68
                ],
                "template": [
                    "materials/iron_light.png",
                    "materials/iron_night.png"
                ]
            }
        },
        "action": {
            "type": "Click"
        },
        "next": [
            "DepartForResource"
        ]
    },
    "ChooseGravel": {
        "recognition": {
            "type": "TemplateMatch",
            "param": {
                "roi": [
                    22,
                    270,
                    316,
                    68
                ],
                "template": [
                    "materials/gravel_light.png",
                    "materials/gravel_night.png"
                ]
            }
        },
        "action": {
            "type": "Click"
        },
        "next": [
            "DepartForResource"
        ]
    },
    "DepartForResource": {
        "recognition": {
            "type": "OCR",
            "param": {
                "roi": [
                    499,
                    318,
                    171,
                    76
                ],
                "expected": [
                    "前往"
                ]
            }
        },
        "action": {
            "type": "Click"
        },
        "next": [
            "ConfirmDepartForResource"
        ],
        "post_delay": 2000
    },
    "ConfirmDepartForResource": {
        "recognition": {
            "type": "OCR",
            "param": {
                "roi": [
                    445,
                    714,
                    98,
                    43
                ],
                "expected": [
                    "确定"
                ]
            }
        },
        "action": {
            "type": "Click"
        },
        "next": [
            "[JumpBack]Loading",
            "[JumpBack]Chat",
            "DigResourceMain"
        ],
        "post_delay": 3000
    },
    "DigResourceMain": {
        "next": [
            "[JumpBack]LocateResource",
            "[JumpBack]AutoDigResource",
            "[JumpBack]SlimeSearch",
            "End"
        ],
        "post_delay": 1000
    },
    "LocateResource": {
        "recognition": {
            "type": "TemplateMatch",
            "param": {
                "template": [
                    "materials/gold_locate.png",
                    "materials/iron_locate.png",
                    "materials/gravel_locate.png"
                ],
                "order_by": "Score"
            }
        },
        "action": {
            "type": "Click"
        },
        "max_hit": 1
    },
    "SlimeSearch": {
        "next": [
            "[JumpBack]KillSlime",
            "[JumpBack]SwipeSlimeUp",
            "[JumpBack]SwipeSlimeDown",
            "[JumpBack]SwipeSlimeUpBack",
            "[JumpBack]SwipeSlimeLeft",
            "[JumpBack]SwipeSlimeRight",
            "[JumpBack]SwipeSlimeLeftBack",
            "End"
        ],
        "max_hit": 1
    },
    "KillSlime": {
        "recognition": {
            "type": "TemplateMatch",
            "param": {
                "template": [
                    "materials/slime.png"
                ]
            }
        },
        "action": {
            "type": "Click"
        },
        "next": [
            "[JumpBack]Loading",
            "[JumpBack]StartFight",
            "CloseByClickBlank"
        ],
        "timeout": 120000 // 两分钟时间等待战斗结束
    },
    "SwipeSlimeUp": {
        "next": [
            "SwipeUp"
        ],
        "max_hit": 2
    },
    "SwipeSlimeDown": {
        "next": [
            "SwipeDown"
        ],
        "max_hit": 4  
    },
    "SwipeSlimeUpBack": {
        "next": [
            "SwipeUp"
        ],
        "max_hit": 2
    },
    "SwipeSlimeLeft": {
        "next": [
            "SwipeLeft"
        ],
        "max_hit": 2
    },
    "SwipeSlimeRight": {
        "next": [
            "SwipeRight"
        ],
        "max_hit": 4
    },
    "SwipeSlimeLeftBack": {
        "next": [
            "SwipeLeft"
        ],
        "max_hit": 2
    },
    "AutoDigResource": {
        "next": [
            "ExhaustEnergy",
            "EndAutoPage",
            "[JumpBack]AutoButton",
            "[JumpBack]StartAutoPage"
        ],
        "max_hit": 1
    },
    "AutoButton": {
        "recognition": {
            "type": "TemplateMatch",
            "param": {
                "template": [
                    "button/auto_button.png"
                ]
            }
        },
        "action": {
            "type": "Click"
        }
    },
    "StartAutoPage": {
        "recognition": {
            "type": "OCR",
            "param": {
                "roi": [
                    295,
                    934,
                    136,
                    43
                ],
                "expected": [
                    "开始托管"
                ]
            }
        },
        "action": {
            "type": "Click",
            "param": {
                "target": [
                    320,
                    859,
                    81,
                    29
                ]
            }
        },
        "next": [
            "InputAutoCount"
        ]
    },
    "InputAutoCount": {
        "action": {
            "type": "InputText",
            "param": {
                "input_text": "6" // 默认6次
            }
        },
        "next": [
            "StartAutoUseEnergy"
        ]
    },
    "StartAutoUseEnergy": {
        "recognition": {
            "type": "OCR",
            "param": {
                "roi": [
                    295,
                    934,
                    136,
                    43
                ],
                "expected": [
                    "开始托管"
                ]
            }
        },
        "action": {
            "type": "Click"
        }
    },
    "EndAutoPage": {
        "recognition": {
            "type": "OCR",
            "param": {
                "roi": [
                    295,
                    934,
                    136,
                    43
                ],
                "expected": [
                    "结束托管"
                ]
            }
        },
        "next": [
            "EndAutoPage",
            "LeaveAutoPage"
        ]
    },
    "LeaveAutoPage": {
        "action": {
            "type": "Click",
            "param": {
                "target": [
                    317,
                    1059,
                    83,
                    37
                ]
            }
        }
    }
}